dynaface/__init__.py
dynaface/config.py
dynaface/const.py
dynaface/facial.py
dynaface/image.py
dynaface/lateral.py
dynaface/measures.py
dynaface/measures_base.py
dynaface/measures_frontal.py
dynaface/measures_lateral.py
dynaface/measures_skin.py
dynaface/models.py
dynaface/util.py
dynaface/version.py
dynaface/__pyinstaller/__init__.py
dynaface/__pyinstaller/hook-dynaface.py
dynaface/spiga/__init__.py
dynaface/spiga/data/__init__.py
dynaface/spiga/data/readme.md
dynaface/spiga/data/__pycache__/__init__.cpython-311.pyc
dynaface/spiga/data/annotations/300wprivate/db_info.json
dynaface/spiga/data/annotations/300wprivate/test.json
dynaface/spiga/data/annotations/300wprivate/train.json
dynaface/spiga/data/annotations/300wpublic/db_info.json
dynaface/spiga/data/annotations/300wpublic/test.json
dynaface/spiga/data/annotations/300wpublic/train.json
dynaface/spiga/data/annotations/cofw68/db_info.json
dynaface/spiga/data/annotations/cofw68/test.json
dynaface/spiga/data/annotations/merlrav/db_info.json
dynaface/spiga/data/annotations/merlrav/test.json
dynaface/spiga/data/annotations/merlrav/train.json
dynaface/spiga/data/annotations/wflw/db_info.json
dynaface/spiga/data/annotations/wflw/test.json
dynaface/spiga/data/annotations/wflw/train.json
dynaface/spiga/data/loaders/__init__.py
dynaface/spiga/data/loaders/dl_config.py
dynaface/spiga/data/loaders/transforms.py
dynaface/spiga/data/loaders/__pycache__/__init__.cpython-311.pyc
dynaface/spiga/data/loaders/__pycache__/dl_config.cpython-311.pyc
dynaface/spiga/data/loaders/__pycache__/transforms.cpython-311.pyc
dynaface/spiga/data/loaders/augmentors/__init__.py
dynaface/spiga/data/loaders/augmentors/landmarks.py
dynaface/spiga/data/loaders/augmentors/modern_posit.py
dynaface/spiga/data/loaders/augmentors/utils.py
dynaface/spiga/data/loaders/augmentors/__pycache__/__init__.cpython-311.pyc
dynaface/spiga/data/loaders/augmentors/__pycache__/landmarks.cpython-311.pyc
dynaface-0.2.4.dist-info/licenses/LICENSE
dynaface-0.2.4.dist-info/METADATA
dynaface-0.2.4.dist-info/WHEEL
dynaface-0.2.4.dist-info/entry_points.txt
dynaface-0.2.4.dist-info/top_level.txt
dynaface-0.2.4.dist-info/RECORD
